scanpy_jupyter_roi/__init__.py
scanpy_jupyter_roi/app.py
scanpy_jupyter_roi-0.1.2.dist-info/LICENSE
scanpy_jupyter_roi-0.1.2.dist-info/METADATA
scanpy_jupyter_roi-0.1.2.dist-info/WHEEL
scanpy_jupyter_roi-0.1.2.dist-info/top_level.txt
scanpy_jupyter_roi-0.1.2.dist-info/RECORD
